{
  "metadata": {
    "category": "hpp",
    "total_patterns": 15,
    "port": 80,
    "description": "k6 test patterns for HTTP Parameter Pollution attacks",
    "phase": "Phase 11"
  },
  "patterns": [
    {
      "id": "HPP_ADMIN_001",
      "name": "Admin privilege escalation via HPP",
      "category": "hpp",
      "subcategory": "privilege_escalation",
      "payload": "&admin=true&role=user",
      "encoded": "%26admin%3Dtrue%26role%3Duser",
      "port": 80,
      "expected_detection": true,
      "severity": "high",
      "expected_rule": "[NGINX HPP] HTTP Parameter Pollution attempt detected"
    },
    {
      "id": "HPP_ADMIN_002",
      "name": "Admin override via HPP",
      "category": "hpp",
      "subcategory": "privilege_escalation",
      "payload": "&override=1&admin=true",
      "encoded": "%26override%3D1%26admin%3Dtrue",
      "port": 80,
      "expected_detection": true,
      "severity": "high",
      "expected_rule": "[NGINX HPP] HTTP Parameter Pollution attempt detected"
    },
    {
      "id": "HPP_DEBUG_001",
      "name": "Debug mode activation via HPP",
      "category": "hpp",
      "subcategory": "debug_activation",
      "payload": "&debug=1&verbose=true",
      "encoded": "%26debug%3D1%26verbose%3Dtrue",
      "port": 80,
      "expected_detection": true,
      "severity": "medium",
      "expected_rule": "[NGINX HPP] HTTP Parameter Pollution attempt detected"
    },
    {
      "id": "HPP_DEBUG_002",
      "name": "Privilege write access via HPP",
      "category": "hpp",
      "subcategory": "privilege_escalation",
      "payload": "&privilege=write&access=admin",
      "encoded": "%26privilege%3Dwrite%26access%3Dadmin",
      "port": 80,
      "expected_detection": true,
      "severity": "high",
      "expected_rule": "[NGINX HPP] HTTP Parameter Pollution attempt detected"
    },
    {
      "id": "HPP_AUTH_001",
      "name": "Authentication bypass via HPP",
      "category": "hpp",
      "subcategory": "auth_bypass",
      "payload": "&authenticated=true",
      "encoded": "%26authenticated%3Dtrue",
      "port": 80,
      "expected_detection": true,
      "severity": "high",
      "expected_rule": "[NGINX HPP] HTTP Parameter Pollution attempt detected"
    },
    {
      "id": "HPP_AUTH_002",
      "name": "Access level override via HPP",
      "category": "hpp",
      "subcategory": "auth_bypass",
      "payload": "&access=all",
      "encoded": "%26access%3Dall",
      "port": 80,
      "expected_detection": true,
      "severity": "high",
      "expected_rule": "[NGINX HPP] HTTP Parameter Pollution attempt detected"
    },
    {
      "id": "HPP_PRIV_001",
      "name": "IsAdmin privilege escalation",
      "category": "hpp",
      "subcategory": "privilege_escalation",
      "payload": "&isadmin=true&privilege=super",
      "encoded": "%26isadmin%3Dtrue%26privilege%3Dsuper",
      "port": 80,
      "expected_detection": true,
      "severity": "high",
      "expected_rule": "[NGINX HPP] HTTP Parameter Pollution attempt detected"
    },
    {
      "id": "HPP_BYPASS_001",
      "name": "Security bypass via HPP",
      "category": "hpp",
      "subcategory": "security_bypass",
      "payload": "&bypass=true&override=1",
      "encoded": "%26bypass%3Dtrue%26override%3D1",
      "port": 80,
      "expected_detection": true,
      "severity": "high",
      "expected_rule": "[NGINX HPP] HTTP Parameter Pollution attempt detected"
    },
    {
      "id": "HPP_WAF_001",
      "name": "HPP WAF bypass + admin escalation",
      "category": "hpp",
      "subcategory": "waf_bypass",
      "payload": "&admin=true&role=user&id=1 OR 1=1",
      "encoded": "%26admin%3Dtrue%26role%3Duser%26id%3D1%20OR%201%3D1",
      "port": 80,
      "expected_detection": true,
      "severity": "high",
      "expected_rule": "[NGINX HPP] HTTP Parameter Pollution attempt detected"
    },
    {
      "id": "HPP_WAF_002",
      "name": "HPP WAF bypass + isadmin",
      "category": "hpp",
      "subcategory": "waf_bypass",
      "payload": "&isadmin=true&role[]=admin",
      "encoded": "%26isadmin%3Dtrue%26role%5B%5D%3Dadmin",
      "port": 80,
      "expected_detection": true,
      "severity": "high",
      "expected_rule": "[NGINX HPP] HTTP Parameter Pollution attempt detected"
    },
    {
      "id": "HPP_FILTER_001",
      "name": "HPP conflicting admin values",
      "category": "hpp",
      "subcategory": "filter_evasion",
      "payload": "&admin=true&role=admin&admin=false&role=user",
      "encoded": "%26admin%3Dtrue%26role%3Dadmin%26admin%3Dfalse%26role%3Duser",
      "port": 80,
      "expected_detection": true,
      "severity": "high",
      "expected_rule": "[NGINX HPP] HTTP Parameter Pollution attempt detected"
    },
    {
      "id": "HPP_FILTER_002",
      "name": "HPP triple override combo",
      "category": "hpp",
      "subcategory": "filter_evasion",
      "payload": "&debug=1&admin=true&override=1",
      "encoded": "%26debug%3D1%26admin%3Dtrue%26override%3D1",
      "port": 80,
      "expected_detection": true,
      "severity": "medium",
      "expected_rule": "[NGINX HPP] HTTP Parameter Pollution attempt detected"
    },
    {
      "id": "HPP_MULTI_001",
      "name": "HPP multi-privilege escalation",
      "category": "hpp",
      "subcategory": "multi_value",
      "payload": "&access=all&privilege=superadmin",
      "encoded": "%26access%3Dall%26privilege%3Dsuperadmin",
      "port": 80,
      "expected_detection": true,
      "severity": "high",
      "expected_rule": "[NGINX HPP] HTTP Parameter Pollution attempt detected"
    },
    {
      "id": "HPP_MULTI_002",
      "name": "HPP auth+bypass combo",
      "category": "hpp",
      "subcategory": "multi_value",
      "payload": "&authenticated=true&bypass=true",
      "encoded": "%26authenticated%3Dtrue%26bypass%3Dtrue",
      "port": 80,
      "expected_detection": true,
      "severity": "high",
      "expected_rule": "[NGINX HPP] HTTP Parameter Pollution attempt detected"
    },
    {
      "id": "HPP_MULTI_003",
      "name": "HPP role escalation",
      "category": "hpp",
      "subcategory": "multi_value",
      "payload": "&role=admin&token=stolen",
      "encoded": "%26role%3Dadmin%26token%3Dstolen",
      "port": 80,
      "expected_detection": true,
      "severity": "high",
      "expected_rule": "[NGINX HPP] HTTP Parameter Pollution attempt detected"
    }
  ]
}
